odoo10_addon_account_invoice_ubl-10.0.1.1.0-nspkg.pth
odoo/addons/account_invoice_ubl/README.rst
odoo/addons/account_invoice_ubl/__init__.py
odoo/addons/account_invoice_ubl/__manifest__.py
odoo/addons/account_invoice_ubl/post_install.py
odoo/addons/account_invoice_ubl/i18n/account_invoice_ubl.pot
odoo/addons/account_invoice_ubl/i18n/es.po
odoo/addons/account_invoice_ubl/i18n/fr.po
odoo/addons/account_invoice_ubl/i18n/pt.po
odoo/addons/account_invoice_ubl/models/__init__.py
odoo/addons/account_invoice_ubl/models/account_config_settings.py
odoo/addons/account_invoice_ubl/models/account_invoice.py
odoo/addons/account_invoice_ubl/models/company.py
odoo/addons/account_invoice_ubl/models/report.py
odoo/addons/account_invoice_ubl/static/description/icon.png
odoo/addons/account_invoice_ubl/tests/__init__.py
odoo/addons/account_invoice_ubl/tests/test_ubl_generate.py
odoo/addons/account_invoice_ubl/views/account_config_settings.xml
odoo/addons/account_invoice_ubl/views/account_invoice.xml
odoo10_addon_account_invoice_ubl-10.0.1.1.0.dist-info/METADATA
odoo10_addon_account_invoice_ubl-10.0.1.1.0.dist-info/WHEEL
odoo10_addon_account_invoice_ubl-10.0.1.1.0.dist-info/namespace_packages.txt
odoo10_addon_account_invoice_ubl-10.0.1.1.0.dist-info/top_level.txt
odoo10_addon_account_invoice_ubl-10.0.1.1.0.dist-info/RECORD
