Metadata-Version: 2.1
Name: odoo10-addon-account-invoice-ubl
Version: 10.0.1.1.0
Summary: Generate UBL XML file for customer invoices/refunds
Home-page: http://www.akretion.com
Author: Akretion,Odoo Community Association (OCA)
Author-email: support@odoo-community.org
License: AGPL-3
Platform: UNKNOWN
Classifier: Programming Language :: Python
Classifier: Framework :: Odoo
Classifier: License :: OSI Approved :: GNU Affero General Public License v3
Requires-Python: ~=2.7
Requires-Dist: odoo10-addon-account-e-invoice-generate
Requires-Dist: odoo10-addon-account-payment-partner
Requires-Dist: odoo10-addon-base-ubl-payment
Requires-Dist: odoo (<10.1dev,>=10.0)
